instabd/__init__.py
instabd/client.py
instabd/exceptions.py
instabd/request.py
instabd/schemas.py
instabd/user_client.py
instabd-0.8.0.dist-info/WHEEL
instabd-0.8.0.dist-info/METADATA
instabd-0.8.0.dist-info/RECORD
